[{"__type__":"cc.SpriteFrame","content":{"name":"default_scrollbar_vertical","texture":"d608qFRoFHwbXd0Dap056i","rect":[0,0,15,30],"offset":[0,0],"originalSize":[15,30],"capInsets":[4,10,4,10]}},[{"__type__":"cc.Prefab","_name":"Grid","data":{"__id__":1}},{"__type__":"cc.Node","_name":"Grid","_components":[{"__type__":"cc.Sprite","node":{"__id__":1},"_materials":[{"__uuid__":"ecpdLyjvZBwrvm+cedCcQy"}],"_spriteFrame":{"__uuid__":"5cO7kybDxGj4ipyMYdRYZB"},"_type":1,"_sizeMode":0}],"_prefab":{"__type__":"cc.PrefabInfo","root":{"__id__":1},"asset":{"__uuid__":"68CdzbEKJCGZVdRX0gSTBP"},"fileId":"b2/z25ReVKErgBwTEKxc3i"},"_contentSize":{"__type__":"cc.Size","width":32,"height":32},"_anchorPoint":{"__type__":"cc.Vec2"},"_trs":{"__type__":"TypedArray","ctor":"Float64Array","array":[0,0,0,0,0,0,1,1,1,1]}}]]